.gitignore
CHANGES.rst
MANIFEST.in
README.rst
README.txt
setup.py
docs/INSTALL.txt
docs/LICENSE.GPL
docs/LICENSE.txt
xm/__init__.py
xm.booking.egg-info/PKG-INFO
xm.booking.egg-info/SOURCES.txt
xm.booking.egg-info/dependency_links.txt
xm.booking.egg-info/entry_points.txt
xm.booking.egg-info/namespace_packages.txt
xm.booking.egg-info/not-zip-safe
xm.booking.egg-info/requires.txt
xm.booking.egg-info/top_level.txt
xm/booking/__init__.py
xm/booking/configure.zcml
xm/booking/tests.py
xm/booking/version.txt
xm/booking/browser/__init__.py
xm/booking/browser/add.pt
xm/booking/browser/add.py
xm/booking/browser/bookings.kss
xm/booking/browser/bookingtable.pt
xm/booking/browser/configure.zcml
xm/booking/browser/viewlets.py
xm/booking/timing/__init__.py
xm/booking/timing/configure.zcml
xm/booking/timing/estimate.zcml
xm/booking/timing/events.py
xm/booking/timing/indexers.py
xm/booking/timing/interfaces.py
xm/booking/timing/tests.txt