Metadata-Version: 1.0
Name: xm.booking
Version: 2.2
Summary: Bookings for eXtremeManagement
Home-page: http://plone.org/products/extreme-management-tool/
Author: Maurits van Rees
Author-email: m.van.rees@zestsoftware.nl
License: GPL
Keywords: eXtremeManagement booking
Platform: UNKNOWN
Classifier: Framework :: Plone
Classifier: Framework :: Zope2
Classifier: Framework :: Zope3
Classifier: Programming Language :: Python
Classifier: Topic :: Software Development :: Libraries :: Python Modules
